<?xml version="1.0" encoding="UTF-8"?>
<objects serializationModel="Studio.02.02.00">
	<object class="AudioFile" id="{a045ea1c-1f0a-4210-a5a3-833e7a8156a7}">
		<property name="assetPath">
			<value>SOPHIE_fx_26.wav</value>
		</property>
		<property name="frequencyInKHz">
			<value>44.0999985</value>
		</property>
		<property name="channelCount">
			<value>2</value>
		</property>
		<property name="length">
			<value>0.56405895691609975</value>
		</property>
		<relationship name="masterAssetFolder">
			<destination>{ade45277-ef5e-405a-b429-ac698260ffc2}</destination>
		</relationship>
	</object>
</objects>
