<?xml version="1.0" encoding="UTF-8"?>
<objects serializationModel="Studio.02.03.00">
	<object class="AudioFile" id="{5eae7caa-9290-48e0-b8dd-7d4e76c1e402}">
		<property name="assetPath">
			<value>Space Gun 15.wav</value>
		</property>
		<property name="frequencyInKHz">
			<value>44.0999985</value>
		</property>
		<property name="channelCount">
			<value>1</value>
		</property>
		<property name="length">
			<value>0.3127891156462585</value>
		</property>
		<relationship name="masterAssetFolder">
			<destination>{ade45277-ef5e-405a-b429-ac698260ffc2}</destination>
		</relationship>
	</object>
</objects>
